paqpy-1.4.1.dist-info/METADATA
paqpy-1.4.1.dist-info/WHEEL
paqpy-1.4.1.dist-info/licenses/LICENSE
paqpy/__init__.py
paqpy/paqpy.pyd
paqpy-1.4.1.dist-info/RECORD
