Metadata-Version: 2.4
Name: paqpy
Version: 1.4.1
Classifier: Intended Audience :: Developers
Classifier: Programming Language :: Rust
Classifier: Programming Language :: Python :: Implementation :: CPython
Classifier: Programming Language :: Python :: Implementation :: PyPy
License-File: LICENSE
Summary: Hash file or directory recursively.
Keywords: hash,directory,file,blake3,rust
Home-Page: https://pypi.org/project/paqpy
Author: gregory langlais
Maintainer: gregory langlais
License-Expression: MIT
Requires-Python: >=3.7
Project-URL: Repository, https://github.com/gregl83/paqpy
Project-URL: Issues, https://github.com/gregl83/paqpy/issues
